.tmuxp.yaml
CHANGES
LICENSE
MANIFEST.in
README.rst
setup.py
doc/api.rst
doc/cli.rst
doc/history.rst
doc/index.rst
requirements/base.txt
requirements/dev.txt
requirements/doc.txt
requirements/test.txt
unihan_tabular/__about__.py
unihan_tabular/__init__.py
unihan_tabular/__main__.py
unihan_tabular/_compat.py
unihan_tabular/process.py
unihan_tabular/test.py
unihan_tabular/util.py
unihan_tabular.egg-info/PKG-INFO
unihan_tabular.egg-info/SOURCES.txt
unihan_tabular.egg-info/dependency_links.txt
unihan_tabular.egg-info/entry_points.txt
unihan_tabular.egg-info/not-zip-safe
unihan_tabular.egg-info/requires.txt
unihan_tabular.egg-info/top_level.txt