Metadata-Version: 1.1
Name: unihan-tabular
Version: 0.8.1
Summary: Export UNIHAN to Python, Data Package, CSV, JSON and YAML
Home-page: https://unihan-tabular.git-pull.com
Author: Tony Narlock
Author-email: cihai@git-pull.com
License: MIT
Download-URL: https://pypi.python.org/pypi/unihan-tabular
Keywords: unihan-tabular
Platform: UNKNOWN
Classifier: Development Status :: 4 - Beta
Classifier: License :: OSI Approved :: MIT License
Classifier: Environment :: Web Environment
Classifier: Intended Audience :: Developers
Classifier: Programming Language :: Python
Classifier: Programming Language :: Python :: 2.7
Classifier: Programming Language :: Python :: 3
Classifier: Programming Language :: Python :: 3.5
Classifier: Programming Language :: Python :: 3.6
Classifier: Programming Language :: Python :: Implementation :: PyPy
Classifier: Topic :: Utilities
Classifier: Topic :: Software Development :: Internationalization
